homocompy/__init__.py
homocompy/stiffness_homogenization.py
homocompy-1.1.1.dist-info/LICENSE
homocompy-1.1.1.dist-info/METADATA
homocompy-1.1.1.dist-info/WHEEL
homocompy-1.1.1.dist-info/top_level.txt
homocompy-1.1.1.dist-info/RECORD
