Metadata-Version: 2.1
Name: homocompy
Version: 1.1.1
Summary: Implementation of analytical homogenization models.
Home-page: UNKNOWN
Author: Ben Van Bavel
Author-email: ben.vanbavel@gmail.com
License: MIT
Platform: UNKNOWN
Classifier: Intended Audience :: Developers
Classifier: License :: OSI Approved :: MIT License
Classifier: Programming Language :: Python
Classifier: Programming Language :: Python :: 3
Classifier: Programming Language :: Python :: 3.6
Classifier: Programming Language :: Python :: 3.7
Classifier: Programming Language :: Python :: 3.8
Classifier: Programming Language :: Python :: 3.9
Classifier: Operating System :: OS Independent
Requires-Dist: numpy
Requires-Dist: matplotlib
